pyalgobox/__init__.py
pyalgobox/pyalgobox.py
pyalgobox-0.0.2.dist-info/METADATA
pyalgobox-0.0.2.dist-info/WHEEL
pyalgobox-0.0.2.dist-info/top_level.txt
pyalgobox-0.0.2.dist-info/RECORD
