Metadata-Version: 2.1
Name: pyalgobox
Version: 0.0.2
Summary: A powerpacked visualisation of Algorithms
Author: Tanay Prabhakar (@tanayprabhakar)
Author-email: <tanayprabhakar10@gmail.com>
Keywords: python,algorithm,data visualisation,college project
Classifier: Development Status :: 1 - Planning
Classifier: Intended Audience :: Developers
Classifier: Programming Language :: Python :: 3
Classifier: Operating System :: Unix
Classifier: Operating System :: MacOS :: MacOS X
Classifier: Operating System :: Microsoft :: Windows
Requires-Dist: matplotlib
Requires-Dist: numpy
